<annotation>
	<folder>images</folder>
	<filename>82.jpg</filename>
	<path>C:\Users\hussj\Documents\L2MLSolution\images\82.jpg</path>
	<source>
		<database>Unknown</database>
	</source>
	<size>
		<width>1012</width>
		<height>806</height>
		<depth>3</depth>
	</size>
	<segmented>0</segmented>
	<object>
		<name>monster</name>
		<pose>Unspecified</pose>
		<truncated>0</truncated>
		<difficult>0</difficult>
		<bndbox>
			<xmin>931</xmin>
			<ymin>90</ymin>
			<xmax>960</xmax>
			<ymax>124</ymax>
		</bndbox>
	</object>
</annotation>
